Metadata-Version: 1.0
Name: skgb-probability
Version: 0.1
Summary: Gaussian and Binomial distributions
Home-page: UNKNOWN
Author: Sumit Kumar
Author-email: sksumit068@gmail.com
License: UNKNOWN
Platform: UNKNOWN
